pyliebherr/__init__.py
pyliebherr/__version__.py
pyliebherr/api.py
pyliebherr/const.py
pyliebherr/exception.py
pyliebherr/models.py
pyliebherr/py.typed
pyliebherr-2026.1.3.dist-info/METADATA
pyliebherr-2026.1.3.dist-info/WHEEL
pyliebherr-2026.1.3.dist-info/RECORD
