Metadata-Version: 2.4
Name: pyliebherr
Version: 2026.1.3
Summary: Helper models to connect to the Liebherr Smart Device Home API.
Project-URL: Homepage, https://github.com/iluvdata/pyliebherr
Project-URL: Issues, https://github.com/iluvdata/pyliebherr/issues
Author-email: iluvdata <gbellsworth@gmail.com>
Classifier: License :: OSI Approved :: MIT License
Classifier: Operating System :: OS Independent
Classifier: Programming Language :: Python :: 3
Classifier: Topic :: Home Automation
Requires-Python: >=3.12
Requires-Dist: aiohttp>=3.7.4
